llyra/__init__.py
llyra/backends/__init__.py
llyra/backends/locals/__init__.py
llyra/backends/locals/defination.py
llyra/backends/locals/utils/__init__.py
llyra/backends/locals/utils/funcs.py
llyra/backends/remotes/__init__.py
llyra/backends/remotes/defination.py
llyra/backends/remotes/backends/__init__.py
llyra/backends/remotes/backends/ollama.py
llyra/backends/remotes/backends/utils/__init__.py
llyra/backends/remotes/backends/utils/funcs.py
llyra/components/__init__.py
llyra/components/configs/__init__.py
llyra/components/configs/basic.py
llyra/components/configs/local.py
llyra/components/configs/remote.py
llyra/components/configs/utils/__init__.py
llyra/components/configs/utils/classes.py
llyra/components/configs/utils/funcs.py
llyra/components/logs/__init__.py
llyra/components/logs/defination.py
llyra/components/logs/utils/__init__.py
llyra/components/logs/utils/classes.py
llyra/components/logs/utils/funcs.py
llyra/components/prompts/__init__.py
llyra/components/prompts/defination.py
llyra/components/prompts/utils/__init__.py
llyra/components/prompts/utils/funcs.py
llyra/components/strategys/__init__.py
llyra/components/strategys/defination.py
llyra/components/strategys/utils/__init__.py
llyra/components/strategys/utils/classes.py
llyra/components/utils/__init__.py
llyra/components/utils/roles.py
llyra/errors/__init__.py
llyra/errors/configs.py
llyra/errors/remotes.py
llyra/errors/strategys.py
llyra/main/__init__.py
llyra/main/defination.py
llyra-0.2.0.dist-info/licenses/LICENSE
llyra-0.2.0.dist-info/METADATA
llyra-0.2.0.dist-info/WHEEL
llyra-0.2.0.dist-info/top_level.txt
llyra-0.2.0.dist-info/RECORD
