Metadata-Version: 2.4
Name: llyra
Version: 0.2.0
Summary: A lightweight interface for calling LLMs with strategy.
Author-email: Albus Shore <dev@albus-shore.net>
License: MIT
Project-URL: Homepage, https://github.com/albus-shore/Llyra
Project-URL: Repository, https://github.com/albus-shore/Llyra
Requires-Python: >=3.8
License-File: LICENSE
Requires-Dist: requests>=2.32.3
Dynamic: license-file
